tritonclient-2.61.0.data/data/LICENSE.txt
tritonclient-2.61.0.data/purelib/tritonclient/__init__.py
tritonclient-2.61.0.data/purelib/tritonclient/_auth.py
tritonclient-2.61.0.data/purelib/tritonclient/_client.py
tritonclient-2.61.0.data/purelib/tritonclient/_plugin.py
tritonclient-2.61.0.data/purelib/tritonclient/_request.py
tritonclient-2.61.0.data/purelib/tritonclient/grpc/__init__.py
tritonclient-2.61.0.data/purelib/tritonclient/grpc/_client.py
tritonclient-2.61.0.data/purelib/tritonclient/grpc/_infer_input.py
tritonclient-2.61.0.data/purelib/tritonclient/grpc/_infer_result.py
tritonclient-2.61.0.data/purelib/tritonclient/grpc/_infer_stream.py
tritonclient-2.61.0.data/purelib/tritonclient/grpc/_requested_output.py
tritonclient-2.61.0.data/purelib/tritonclient/grpc/_utils.py
tritonclient-2.61.0.data/purelib/tritonclient/grpc/model_config_pb2.py
tritonclient-2.61.0.data/purelib/tritonclient/grpc/service_pb2.py
tritonclient-2.61.0.data/purelib/tritonclient/grpc/service_pb2_grpc.py
tritonclient-2.61.0.data/purelib/tritonclient/grpc/aio/__init__.py
tritonclient-2.61.0.data/purelib/tritonclient/grpc/aio/auth/__init__.py
tritonclient-2.61.0.data/purelib/tritonclient/grpc/auth/__init__.py
tritonclient-2.61.0.data/purelib/tritonclient/http/__init__.py
tritonclient-2.61.0.data/purelib/tritonclient/http/_client.py
tritonclient-2.61.0.data/purelib/tritonclient/http/_infer_input.py
tritonclient-2.61.0.data/purelib/tritonclient/http/_infer_result.py
tritonclient-2.61.0.data/purelib/tritonclient/http/_requested_output.py
tritonclient-2.61.0.data/purelib/tritonclient/http/_utils.py
tritonclient-2.61.0.data/purelib/tritonclient/http/aio/__init__.py
tritonclient-2.61.0.data/purelib/tritonclient/http/aio/auth/__init__.py
tritonclient-2.61.0.data/purelib/tritonclient/http/auth/__init__.py
tritonclient-2.61.0.data/purelib/tritonclient/utils/__init__.py
tritonclient-2.61.0.data/purelib/tritonclient/utils/_dlpack.py
tritonclient-2.61.0.dist-info/LICENSE.txt
tritonclient-2.61.0.dist-info/METADATA
tritonclient-2.61.0.dist-info/WHEEL
tritonclient-2.61.0.dist-info/top_level.txt
tritonclient-2.61.0.dist-info/RECORD
