Metadata-Version: 2.1
Name: tritonclient
Version: 2.61.0
Summary: Python client library and utilities for communicating with Triton Inference Server
Home-page: https://developer.nvidia.com/nvidia-triton-inference-server
Author: NVIDIA Inc.
Author-email: sw-dl-triton@nvidia.com
License: BSD
Keywords: grpc,http,triton,tensorrt,inference,server,service,client,nvidia
Classifier: Development Status :: 5 - Production/Stable
Classifier: Intended Audience :: Developers
Classifier: Intended Audience :: Science/Research
Classifier: Intended Audience :: Information Technology
Classifier: Topic :: Scientific/Engineering
Classifier: Topic :: Scientific/Engineering :: Image Recognition
Classifier: Topic :: Scientific/Engineering :: Artificial Intelligence
Classifier: Topic :: Software Development :: Libraries
Classifier: Topic :: Utilities
Classifier: License :: OSI Approved :: BSD License
Classifier: Programming Language :: Python :: 3
Classifier: Programming Language :: Python :: 3.6
Classifier: Programming Language :: Python :: 3.7
Classifier: Programming Language :: Python :: 3.8
Classifier: Environment :: Console
Classifier: Natural Language :: English
Classifier: Operating System :: OS Independent
License-File: LICENSE.txt
Requires-Dist: numpy >=1.19.1
Requires-Dist: perf-analyzer
Requires-Dist: python-rapidjson >=0.9.1
Requires-Dist: urllib3 >=2.0.7
Provides-Extra: all
Requires-Dist: aiohttp <4.0.0,>=3.8.1 ; extra == 'all'
Requires-Dist: cuda-python ; extra == 'all'
Requires-Dist: geventhttpclient >=2.3.3 ; extra == 'all'
Requires-Dist: grpcio <1.68,>=1.63.0 ; extra == 'all'
Requires-Dist: numpy >=1.19.1 ; extra == 'all'
Requires-Dist: packaging >=14.1 ; extra == 'all'
Requires-Dist: protobuf <6.0dev,>=5.26.1 ; extra == 'all'
Requires-Dist: python-rapidjson >=0.9.1 ; extra == 'all'
Provides-Extra: cuda
Requires-Dist: cuda-python ; extra == 'cuda'
Provides-Extra: grpc
Requires-Dist: grpcio <1.68,>=1.63.0 ; extra == 'grpc'
Requires-Dist: numpy >=1.19.1 ; extra == 'grpc'
Requires-Dist: packaging >=14.1 ; extra == 'grpc'
Requires-Dist: protobuf <6.0dev,>=5.26.1 ; extra == 'grpc'
Requires-Dist: python-rapidjson >=0.9.1 ; extra == 'grpc'
Provides-Extra: http
Requires-Dist: aiohttp <4.0.0,>=3.8.1 ; extra == 'http'
Requires-Dist: geventhttpclient >=2.3.3 ; extra == 'http'
Requires-Dist: numpy >=1.19.1 ; extra == 'http'
Requires-Dist: python-rapidjson >=0.9.1 ; extra == 'http'
